{"uid":"internal-new-slices","slug":"internal/new-slices-test","body":[{"key":"call_to_action$40a8329a-a291-4d17-bfe1-d3404686b263","value":{"variation":"downloadRoutePlanner","items":[{}],"primary":{"title":"Title goes here","description":"And here's a lengthy description","ctaLink":{"url":"https://zombo.com","preview":null,"target":"_blank"},"ctaText":"Welcome"}}},{"key":"call_to_action$a7f1b216-d4b7-4d2b-8ced-67c2edea24e8","value":{"variation":"downloadTeams","items":[{}],"primary":{"title":"CTA Title","description":"Here goes a catchy and engaging tagline","ctaText":"Download it, download it now"}}},{"key":"content_collection$fdad749c-55f9-4341-b680-87dbe0db87d8","value":{"variation":"withFeatured","items":[{}],"primary":{"title":"yoooo","featured":{"id":"YebXhxEAACAAqWtC","wioUrl":"wio://documents/YebXhxEAACAAqWtC"}}}},{"key":"content_collection$286fc104-5fa2-4add-a65f-19c7f1e342c0","value":{"variation":"withImageAndTextCards","items":[{"content":{"id":"YebXhxEAACAAqWtC","wioUrl":"wio://documents/YebXhxEAACAAqWtC"}},{"content":{"id":"YebXhxEAACAAqWtC","wioUrl":"wio://documents/YebXhxEAACAAqWtC"}},{"content":{"id":"YebXhxEAACAAqWtC","wioUrl":"wio://documents/YebXhxEAACAAqWtC"}}],"primary":{"title":"For drivers","featured":{"id":"YebXhxEAACAAqWtC","wioUrl":"wio://documents/YebXhxEAACAAqWtC"}}}},{"key":"content_collection$d736695d-8313-4a53-b962-5cdea5b92958","value":{"variation":"withImageCards","items":[{"content":{"id":"YebXhxEAACAAqWtC","wioUrl":"wio://documents/YebXhxEAACAAqWtC"}},{"content":{"id":"YebXhxEAACAAqWtC","wioUrl":"wio://documents/YebXhxEAACAAqWtC"}},{"content":{"id":"YebXhxEAACAAqWtC","wioUrl":"wio://documents/YebXhxEAACAAqWtC"}}],"primary":{"title":"title with cards"}}},{"key":"content_collection$ac4592d6-1ec8-41b9-8eb9-70f991f66874","value":{"variation":"withTextCards","items":[{"content":{"id":"YebXhxEAACAAqWtC","wioUrl":"wio://documents/YebXhxEAACAAqWtC"}},{"content":{"id":"YebXhxEAACAAqWtC","wioUrl":"wio://documents/YebXhxEAACAAqWtC"}},{"content":{"id":"YebXhxEAACAAqWtC","wioUrl":"wio://documents/YebXhxEAACAAqWtC"}},{"content":{"id":"YebXhxEAACAAqWtC","wioUrl":"wio://documents/YebXhxEAACAAqWtC"}}],"primary":{"title":"with text cards"}}},{"key":"content_collection$7f962a96-56e4-41ca-b673-65aa1c49b16f","value":{"variation":"withTwoImageCards","items":[{"content":{"id":"YebXhxEAACAAqWtC","wioUrl":"wio://documents/YebXhxEAACAAqWtC"}},{"content":{"id":"YebXhxEAACAAqWtC","wioUrl":"wio://documents/YebXhxEAACAAqWtC"}},{"content":{"id":"YebXhxEAACAAqWtC","wioUrl":"wio://documents/YebXhxEAACAAqWtC"}}],"primary":{"title":"with two image cards"}}},{"key":"signage$30e641f3-d89e-4f3a-b2a3-d3627e22f288","value":{"variation":"default-slice","items":[{"title":"title","description":[{"type":"paragraph","content":{"text":"description","spans":[]}}],"palette":"blue"},{"title":"title","description":[{"type":"paragraph","content":{"text":"description","spans":[]}}],"palette":"teal"},{"title":"title","description":[{"type":"paragraph","content":{"text":"description","spans":[]}}],"palette":"yellow"}],"primary":{}}},{"key":"tag_list$9ef11ad4-bb4d-411d-9d83-b6353b2e0295","value":{"variation":"default-slice","items":[{}],"primary":{"title":"Test","navigation":{"id":"YgVvvREAAB0AMRpF","wioUrl":"wio://documents/YgVvvREAAB0AMRpF"}}}},{"key":"testrelationship$da6018c0-e73a-41b6-ba3b-a89971f71434","value":{"repeat":[{}],"non-repeat":{"relationship":{"id":"YebXhxEAACAAqWtC","wioUrl":"wio://documents/YebXhxEAACAAqWtC"}}}}],"social_cards":[{}],"follow_index":true,"footer_document_id":{"id":"YPcbQBIAAFwbeNZF","wioUrl":"wio://documents/YPcbQBIAAFwbeNZF"},"header_document_id":{"id":"YcTuihAAACAApcma","wioUrl":"wio://documents/YcTuihAAACAApcma"},"type":"page","tags":[],"lang":"en-us","grouplang":"YfF3pBEAACIA1-Na"}