{"name":"Blog footer nav","nav":[{"key":"nav_item$86df04ff-80ef-4117-8cdc-36f4c7259dfc","value":{"repeat":[{"sub_nav_link_label":"Make money"}],"non-repeat":{"label":"Tags"}}},{"key":"nav_item$3078dc2a-5668-4872-a9ac-157bdd771af9","value":{"repeat":[{"sub_nav_link_label":"Most read 1","sub_nav_link":{"url":"https://getcircuit.com","preview":null}}],"non-repeat":{"label":"Most read"}}},{"key":"nav_item$835966b2-a405-46c7-a08e-a330a9db59f5","value":{"repeat":[{"sub_nav_link_label":"Guide 1"}],"non-repeat":{"label":"Guides"}}},{"key":"nav_item$bcc1ff6d-dcd0-4988-8ea6-a743c0e345b1","value":{"repeat":[{"sub_nav_link_label":"About"}],"non-repeat":{"label":"Circuit"}}}],"ctas":[{}],"type":"navigation","tags":["CircuitBlog"],"lang":"en-us","grouplang":"YgVvvREAAB0AMRpH"}